setup.cfg
setup.py
stock_symbols/__init__.py
stock_symbols/symbol_helper.py
stock_symbols/symbols.py
stock_symbols.egg-info/PKG-INFO
stock_symbols.egg-info/SOURCES.txt
stock_symbols.egg-info/dependency_links.txt
stock_symbols.egg-info/requires.txt
stock_symbols.egg-info/top_level.txt