Metadata-Version: 1.1
Name: stock-symbols
Version: 0.5.3
Summary: Retrieves list of all symbols present in SP500, NASDAQ, AMEX and NYSE
Home-page: https://github.com/huangyunict/stock_symbols
Author: Yun Huang
Author-email: huangyunict@gmail.com
License: GNU LGPLv2+
Download-URL: http://pypi.python.org/pypi/stock_symbols
Keywords: stocks,stockmarket,yahoo,finance,SP500,NASDAQ,AMEX,NYSE
Platform: UNKNOWN
Classifier: Development Status :: 4 - Beta
Classifier: Intended Audience :: Developers
Classifier: License :: OSI Approved :: GNU Lesser General Public License v2 or later (LGPLv2+)
Classifier: Topic :: Software Development :: Libraries :: Python Modules
Classifier: Topic :: Office/Business :: Financial :: Investment
